ecache/__init__.py
ecache/core.py
ecache/db.py
ecache/hook.py
ecache/ext/__init__.py
ecache/ext/example.py
ecache/ext/flask_cache.py
ecache-0.1.2.dist-info/DESCRIPTION.rst
ecache-0.1.2.dist-info/METADATA
ecache-0.1.2.dist-info/metadata.json
ecache-0.1.2.dist-info/RECORD
ecache-0.1.2.dist-info/top_level.txt
ecache-0.1.2.dist-info/WHEEL
include/meepo/setup.py
tests/__init__.py
tests/conftest.py
tests/test_cache_mixin.py
tests/test_db.py
