Metadata-Version: 2.0
Name: ecache
Version: 0.1.2
Summary: Cache integration with sqlalchemy.
Home-page: https://github.com/MrKiven/ECache
Author: Mrkiven
Author-email: kiven.mr@gmail.com
License: MIT
Platform: UNKNOWN
Requires-Dist: SQLAlchemy (==0.9.3)
Requires-Dist: redis (>=2.10.5)
Requires-Dist: flask (>=0.10.1)
Requires-Dist: Flask-SQLAlchemy (==2.1)
Requires-Dist: dogpile.cache (==0.5.4)
Requires-Dist: meepo (>=0.18)
Requires-Dist: blinker (>=1.3)
